SVGCompress/__init__.py
SVGCompress/create_testplot.py
SVGCompress/svg_compression.py
SVGCompress/vector_utils.py
SVGCompress/wrap_scour.py
SVGCompress/test/bitmap_and_vector.svg
SVGCompress/test/map_test.svg
SVGCompress/test/map_test_hull.svg
SVGCompress/test/map_test_hull_opt.svg
SVGCompress/test/map_test_merged.svg
SVGCompress/test/map_test_merged_opt.svg
SVGCompress/test/map_test_opt.svg
SVGCompress/test/map_test_simplified.svg
SVGCompress/test/map_test_simplified_opt.svg
SVGCompress/test/map_test_truncbybboxarea.svg
SVGCompress/test/map_test_truncbybboxarea_opt.svg
SVGCompress/test/map_test_truncbycircumference.svg
SVGCompress/test/map_test_truncbycircumference_opt.svg
SVGCompress/test/map_test_uncompressed.svg
SVGCompress/test/matplotlib_test.svg
SVGCompress/test/matplotlib_test_hull.svg
SVGCompress/test/matplotlib_test_hull_opt.svg
SVGCompress/test/matplotlib_test_merged.svg
SVGCompress/test/matplotlib_test_merged_opt.svg
SVGCompress/test/matplotlib_test_opt.svg
SVGCompress/test/matplotlib_test_simplified.svg
SVGCompress/test/matplotlib_test_simplified_opt.svg
SVGCompress/test/matplotlib_test_truncbybboxarea.svg
SVGCompress/test/matplotlib_test_truncbybboxarea_opt.svg
SVGCompress/test/matplotlib_test_truncbycircumference.svg
SVGCompress/test/matplotlib_test_truncbycircumference_opt.svg
SVGCompress/test/matplotlib_test_uncompressed.svg
SVGCompress/test/test_vector.jpg
SVGCompress/test/test_vector.svg
SVGCompress/test/test_vector_compressed.jpg
SVGCompress/test/test_vector_hull.svg
SVGCompress/test/test_vector_hull_opt.svg
SVGCompress/test/test_vector_merged.svg
SVGCompress/test/test_vector_merged_opt.svg
SVGCompress/test/test_vector_opt.svg
SVGCompress/test/test_vector_simplified.svg
SVGCompress/test/test_vector_simplified_opt.svg
SVGCompress/test/test_vector_truncbybboxarea.svg
SVGCompress/test/test_vector_truncbybboxarea_opt.svg
SVGCompress/test/test_vector_truncbycircumference.svg
SVGCompress-0.60.dist-info/DESCRIPTION.rst
SVGCompress-0.60.dist-info/METADATA
SVGCompress-0.60.dist-info/metadata.json
SVGCompress-0.60.dist-info/RECORD
SVGCompress-0.60.dist-info/top_level.txt
SVGCompress-0.60.dist-info/WHEEL
