Metadata-Version: 2.0
Name: SVGCompress
Version: 0.60
Summary: Compress svg graphics
Home-page: UNKNOWN
Author: Gen Del Raye
Author-email: gdelraye@hawaii.edu
License: UNKNOWN
Keywords: figure,vector,svg,compression
Platform: UNKNOWN
Classifier: Intended Audience :: Science/Research
Classifier: License :: OSI Approved :: GNU General Public License v3 (GPLv3)
Classifier: Natural Language :: English
Classifier: Operating System :: OS Independent
Classifier: Programming Language :: Python
Classifier: Topic :: Scientific/Engineering
Classifier: Topic :: Scientific/Engineering :: Visualization
Requires-Dist: svg.path
Requires-Dist: rdp
Requires-Dist: lxml
Requires-Dist: scour
